context_curse/__init__.py
context_curse/__main__.py
context_curse/thing.py
context_curse-0.0.3.dist-info/METADATA
context_curse-0.0.3.dist-info/WHEEL
context_curse-0.0.3.dist-info/entry_points.txt
context_curse-0.0.3.dist-info/top_level.txt
context_curse-0.0.3.dist-info/RECORD
