Metadata-Version: 2.1
Name: context_curse
Version: 0.0.3
Summary: A CLI tool for managing files and directories before feeding them into an LLM.
Home-page: https://github.com/bin2ai/context_curse
Classifier: Programming Language :: Python :: 3
Classifier: License :: OSI Approved :: MIT License
Classifier: Operating System :: OS Independent
Requires-Python: >=3.6
Requires-Dist: windows-curses; platform_system == "Windows"
